MANIFEST.in
README.rst
setup.py
cms/__init__.py
cms/admin.py
cms/context_processors.py
cms/dashboard.py
cms/dashboard_modules.py
cms/forms.py
cms/html.py
cms/middleware.py
cms/permalinks.py
cms/sitemaps.py
cms/tokens.py
cms/views.py
cms/apps/__init__.py
cms/apps/links/__init__.py
cms/apps/links/models.py
cms/apps/links/urls.py
cms/apps/links/views.py
cms/apps/links/migrations/0001_initial.py
cms/apps/links/migrations/0002_auto_20171020_1320.py
cms/apps/links/migrations/__init__.py
cms/apps/links/static/links/img/link.png
cms/apps/links/tests/__init__.py
cms/apps/links/tests/test_urls.py
cms/apps/links/tests/test_views.py
cms/apps/media/__init__.py
cms/apps/media/admin.py
cms/apps/media/filetypes.py
cms/apps/media/forms.py
cms/apps/media/models.py
cms/apps/media/utils.py
cms/apps/media/widgets.py
cms/apps/media/migrations/0001_initial.py
cms/apps/media/migrations/0002_auto_20150713_1408.py
cms/apps/media/migrations/0003_file_alt_text.py
cms/apps/media/migrations/0004_auto_20170407_1442.py
cms/apps/media/migrations/0005_auto_20171107_1537.py
cms/apps/media/migrations/0006_remove_video_webm.py
cms/apps/media/migrations/0007_auto_20180801_1419.py
cms/apps/media/migrations/0008_auto_20180801_1633.py
cms/apps/media/migrations/0009_auto_20181207_1318.py
cms/apps/media/migrations/0010_auto_20190523_1638.py
cms/apps/media/migrations/0011_auto_20200406_1508.py
cms/apps/media/migrations/0012_auto_20210418_2350.py
cms/apps/media/migrations/0013_video_duration.py
cms/apps/media/migrations/0014_auto_20210520_1043.py
cms/apps/media/migrations/__init__.py
cms/apps/media/static/media/img/audio-x-generic.png
cms/apps/media/static/media/img/image-x-generic.png
cms/apps/media/static/media/img/text-x-generic-template.png
cms/apps/media/static/media/img/text-x-generic.png
cms/apps/media/static/media/img/video-x-generic.png
cms/apps/media/static/media/img/x-office-document.png
cms/apps/media/static/media/img/x-office-spreadsheet.png
onespacemedia_cms.egg-info/PKG-INFO
onespacemedia_cms.egg-info/SOURCES.txt
onespacemedia_cms.egg-info/dependency_links.txt
onespacemedia_cms.egg-info/not-zip-safe
onespacemedia_cms.egg-info/requires.txt
onespacemedia_cms.egg-info/top_level.txt