Metadata-Version: 2.1
Name: onespacemedia-cms
Version: 5.0.3
Summary: CMS used by Onespacemedia
Home-page: https://github.com/onespacemedia/cms
Author: Onespacemedia
Author-email: developers@onespacemedia.com
License: BSD
Platform: UNKNOWN
Classifier: Development Status :: 5 - Production/Stable
Classifier: Framework :: Django :: 2.2
Classifier: Framework :: Django :: 3.1
Classifier: Intended Audience :: Developers
Classifier: License :: OSI Approved :: BSD License
Classifier: Natural Language :: English
Classifier: Programming Language :: Python :: 3.6
Provides-Extra: usertools
Provides-Extra: testing
Provides-Extra: geoip
